odoo8_addon_website_mail_snippet_bg_color-8.0.1.0.0.99.dev10-py2.7-nspkg.pth
odoo8_addon_website_mail_snippet_bg_color-8.0.1.0.0.99.dev10.dist-info/DESCRIPTION.rst
odoo8_addon_website_mail_snippet_bg_color-8.0.1.0.0.99.dev10.dist-info/METADATA
odoo8_addon_website_mail_snippet_bg_color-8.0.1.0.0.99.dev10.dist-info/RECORD
odoo8_addon_website_mail_snippet_bg_color-8.0.1.0.0.99.dev10.dist-info/WHEEL
odoo8_addon_website_mail_snippet_bg_color-8.0.1.0.0.99.dev10.dist-info/metadata.json
odoo8_addon_website_mail_snippet_bg_color-8.0.1.0.0.99.dev10.dist-info/namespace_packages.txt
odoo8_addon_website_mail_snippet_bg_color-8.0.1.0.0.99.dev10.dist-info/top_level.txt
odoo_addons/website_mail_snippet_bg_color/README.rst
odoo_addons/website_mail_snippet_bg_color/__init__.py
odoo_addons/website_mail_snippet_bg_color/__openerp__.py
odoo_addons/website_mail_snippet_bg_color/i18n/de.po
odoo_addons/website_mail_snippet_bg_color/i18n/es.po
odoo_addons/website_mail_snippet_bg_color/i18n/fr.po
odoo_addons/website_mail_snippet_bg_color/i18n/sl.po
odoo_addons/website_mail_snippet_bg_color/images/click_option.png
odoo_addons/website_mail_snippet_bg_color/images/color_picker.png
odoo_addons/website_mail_snippet_bg_color/images/color_set.png
odoo_addons/website_mail_snippet_bg_color/static/description/icon.png
odoo_addons/website_mail_snippet_bg_color/static/src/js/bg_color_picker.js
odoo_addons/website_mail_snippet_bg_color/views/assets.xml
odoo_addons/website_mail_snippet_bg_color/views/snippets.xml
