Metadata-Version: 2.0
Name: odoo8-addon-website-mail-snippet-bg-color
Version: 8.0.1.0.0.99.dev10
Summary: Set any background color for any mail editor snippet
Home-page: http://www.antiun.com
Author: Antiun Ingeniería S.L., Odoo Community Association (OCA)
Author-email: support@odoo-community.org
License: AGPL-3
Platform: UNKNOWN
Classifier: Programming Language :: Python :: 2.7
Classifier: Framework :: Odoo
Classifier: License :: OSI Approved :: GNU Affero General Public License v3
Requires-Dist: odoo (<9.0a,>=8.0a)
